pixiver/__init__.py
pixiver/basiciv.py
pixiver/exceptions.py
pixiver/helper.py
pixiver/pixiv.py
pixiver/rankiv.py
pixiver/tagiv.py
pixiver/useriv.py
pixiver/worksiv.py
pixiver-0.0.9.1252.dist-info/LICENSE
pixiver-0.0.9.1252.dist-info/METADATA
pixiver-0.0.9.1252.dist-info/WHEEL
pixiver-0.0.9.1252.dist-info/top_level.txt
pixiver-0.0.9.1252.dist-info/RECORD
