Metadata-Version: 2.1
Name: pixiver
Version: 0.0.9.1252
Summary: This is a python package for get illustration on the pixiv by ajax interfaces.
Home-page: https://github.com/darkchii/pixiver
Author: darkchii
Author-email: darkchii@qq.com
License: UNKNOWN
Platform: UNKNOWN
Classifier: Development Status :: 2 - Pre-Alpha
Classifier: License :: OSI Approved :: MIT License
Classifier: Programming Language :: Python :: 3
Classifier: Topic :: Software Development :: Libraries :: Python Modules
Classifier: Topic :: Internet
Requires-Dist: requests
Requires-Dist: pillow
